psyl/__init__.py
psyl/lisp.py
psyl-0.9.0.dist-info/LICENSE
psyl-0.9.0.dist-info/METADATA
psyl-0.9.0.dist-info/WHEEL
psyl-0.9.0.dist-info/top_level.txt
psyl-0.9.0.dist-info/RECORD
